{
  "wave": "P4",
  "platformDataByPlayer": {
    "candA": [
      { "platform": "instagram", "followers": 123000, "posts": 45, "engagementPct": 2.1, "likes": 54000, "comments": 1800, "shares": 900, "views": 780000, "mentions": 1200 },
      { "platform": "x", "followers": 45000, "posts": 90, "engagementPct": 1.2, "likes": 12000, "comments": 900, "shares": 1500, "views": 350000, "mentions": 600 }
    ],
    "candB": [
      { "platform": "instagram", "followers": 98000, "posts": 30, "engagementPct": 1.7, "likes": 32000, "comments": 1100, "shares": 700, "views": 540000, "mentions": 800 }
    ]
  }
}
